ezinfer/base_infer/__init__.py
ezinfer/base_infer/base_infer.py
ezinfer/mxnet_infer/__init__.py
ezinfer/mxnet_infer/mxnet_infer.py
ezinfer/onnx_infer/__init__.py
ezinfer/onnx_infer/onnx_infer.py
ezinfer/pytorch_infer/__init__.py
ezinfer/pytorch_infer/pytorch_infer.py
ezinfer/tensorflow_infer/__init__.py
ezinfer/tensorflow_infer/tensorflow_infer.py
ezinfer-0.0.1.dist-info/LICENSE
ezinfer-0.0.1.dist-info/METADATA
ezinfer-0.0.1.dist-info/WHEEL
ezinfer-0.0.1.dist-info/top_level.txt
ezinfer-0.0.1.dist-info/RECORD
