Metadata-Version: 2.1
Name: ezinfer
Version: 0.0.1
Summary: EZInfer - An API Wrapper for Mainstream Python DL Backends.
Author-email: Arian Tashakkor <a77physics@gmail.com>
License: GNU GENERAL PUBLIC LICENSE
Project-URL: Homepage, https://github.com/ArianARIAPA/ez-infer
Keywords: deep learning,onnx,pytorch,tensorflow,mxnet
Classifier: Programming Language :: Python :: 3
Requires-Python: >=3.8
License-File: LICENSE
